{
  "generator-jhipster": {
    "applicationType": "microservice",
    "gitHubOrganization": "ada-hou",
    "baseName": "jhipsterSampleApplication",
    "packageName": "io.github.jhipster.application",
    "serverPort": 8081,
    "serviceDiscoveryType": "eureka",
    "authenticationType": "jwt",
    "uaaBaseName": "../uaa",
    "cacheProvider": "hazelcast",
    "enableHibernateCache": true,
    "websocket": false,
    "databaseType": "sql",
    "devDatabaseType": "mysql",
    "prodDatabaseType": "mysql",
    "searchEngine": false,
    "enableSwaggerCodegen": "true",
    "messageBroker": "kafka",
    "buildTool": "maven",
    "enableSocialSignIn": false,
    "useSass": false,
    "clientPackageManager": "yarn",
    "testFrameworks": [],
    "enableTranslation": false,
    "nativeLanguage": "zh-cn",
    "languages": [
      "en"
    ],
    "clientFramework": "angularX",
    "jhipsterVersion": "4.14.3",
    "packageFolder": "io/github/jhipster/application",
    "jwtSecretKey": "fd44cc293111c45d7adf6d1574ffd3826167d449",
    "jhiPrefix": "jhi",
    "skipClient": true,
    "skipUserManagement": true
  }
}